modelestimator/__init__.py
modelestimator/_controller.py
modelestimator/bootstrap.py
modelestimator/io.py
modelestimator/main.py
modelestimator/version.py
modelestimator/_bootstraper/__init__.py
modelestimator/_bootstraper/bootstraper.py
modelestimator/_bw_estimator/__init__.py
modelestimator/_bw_estimator/bw_estimator.py
modelestimator/_bw_estimator/_calculate_q_eq/__init__.py
modelestimator/_bw_estimator/_calculate_q_eq/calculate_q_eq.py
modelestimator/_bw_estimator/_calculate_q_eq/comp_posterior.py
modelestimator/_bw_estimator/_calculate_q_eq/comp_posterior_JC.py
modelestimator/_bw_estimator/_calculate_q_eq/create_count_matrices.py
modelestimator/_bw_estimator/_calculate_q_eq/estimate_q.py
modelestimator/_bw_estimator/_calculate_q_eq/iterative_estimation.py
modelestimator/_bw_estimator/_calculate_q_eq/match_closest_pair.py
modelestimator/_bw_estimator/_calculate_q_eq/matrix_weight.py
modelestimator/_bw_estimator/_calculate_q_eq/simple_estimation.py
modelestimator_v2-2.1.4.dist-info/LICENSE
modelestimator_v2-2.1.4.dist-info/METADATA
modelestimator_v2-2.1.4.dist-info/WHEEL
modelestimator_v2-2.1.4.dist-info/entry_points.txt
modelestimator_v2-2.1.4.dist-info/top_level.txt
modelestimator_v2-2.1.4.dist-info/RECORD
