Metadata-Version: 2.1
Name: modelestimator-v2
Version: 2.1.4
Summary: Program for estimating amino acid replacement rates
Author: Ruben Ridderström
Author-email: Lars Arvestad <arve@math.su.se>
Maintainer-email: Lars Arvestad <arve@math.su.se>
License: GNU General Public License v3 (GPLv3)
Project-URL: homepage, https://github.com/arvestad/modelestimator-v2
Classifier: Programming Language :: Python :: 3
Classifier: License :: OSI Approved :: GNU General Public License v3 (GPLv3)
Classifier: Operating System :: OS Independent
Classifier: Topic :: Scientific/Engineering :: Bio-Informatics
License-File: LICENSE
Requires-Dist: scipy >=1.1
Requires-Dist: numpy >=1.14
Requires-Dist: biopython >=1.70
